pythonz_enum-0.2.1.dist-info/METADATA
pythonz_enum-0.2.1.dist-info/WHEEL
pythonz_enum/__init__.py
pythonz_enum/base.py
pythonz_enum/maybe.py
pythonz_enum/result.py
pythonz_enum-0.2.1.dist-info/RECORD
