Metadata-Version: 2.1
Name: pythonz_enum
Version: 0.2.1
Summary: enums for pythonz
Author-Email: Yuichiro Smith <yu-ichiro@s3i7h.com>
License: MIT
Requires-Python: >=3.8
Requires-Dist: pythonz_pipe>=0.1.1
